rtl/pulse_sync.v
module pulse_synchronizer (	input clk_a,
				input clk_b,
				input pulse_in,
				input a_reset,
				output reg pulse_out );
				
	reg q_a, q_b1, q_b2, q_b3;		
	
	always@(posedge clk_a or posedge a_reset)			//domain A converting pulse to level
	begin
		if(a_reset == 1'b1)
			q_a <= 1'b0;
		
		else if(pulse_in == 1'b1)
			q_a <= ~q_a;
	end
	
	always@(posedge clk_b or posedge a_reset)			//domain B logic
	begin
		if(a_reset == 1'b1)
			{q_b1, q_b2, q_b3, pulse_out} <= 4'd0;
		
		else
		begin
			q_b1 <= q_a;
			q_b2 <= q_b1;
			q_b3 <= q_b2;
			pulse_out <= q_b2 ^ q_b3;
		end
	end		
endmodule

tb/pulse_sync_tb.v
`timescale 1ns/1ps

module pulse_sync_tb;
	reg clk_a;
	reg clk_b;
	reg pulse_in;
	reg a_reset;
	wire pulse_out;
	
	pulse_synchronizer DUT (	.clk_a(clk_a),
					.clk_b(clk_b),
					.pulse_in(pulse_in),
					.a_reset(a_reset),
					.pulse_out(pulse_out)
				);
	
	initial
	begin
		$dumpfile("simulation.vcd"); // Creates the file
    		$dumpvars(0, pulse_sync_tb);  // Dumps ALL signals in this module and below
	end
				
	task reset_dut;
	begin
		@(negedge clk_a);
			a_reset = 1'b1;
			pulse_in = 1'b0;
		
		@(negedge clk_b);
		@(negedge clk_b);
		
		@(negedge clk_a);
			a_reset = 1'b0;
	end
	endtask
	
	task send_pulse;
	begin
		@(negedge clk_a);
			pulse_in = 1'b1;
			
		@(negedge clk_a);
			pulse_in = 1'b0;
	end
	endtask
	
	initial
		{clk_a, clk_b} = 2'd0;
		
	always
		#5 clk_a = ~clk_a;
	
	always
		#12.5 clk_b = ~clk_b;
	
	initial
	begin
		reset_dut();
				
		#20 send_pulse();
		
		#500 $finish;
	end
	
endmodule

sim/simulation.vcd
$date
	Mon Apr 20 19:04:29 2026
$end
$version
	Icarus Verilog
$end
$timescale
	1ps
$end
$scope module pulse_sync_tb $end
$var wire 1 ! pulse_out $end
$var reg 1 " a_reset $end
$var reg 1 # clk_a $end
$var reg 1 $ clk_b $end
$var reg 1 % pulse_in $end
$scope module DUT $end
$var wire 1 " a_reset $end
$var wire 1 # clk_a $end
$var wire 1 $ clk_b $end
$var wire 1 % pulse_in $end
$var reg 1 ! pulse_out $end
$var reg 1 & q_a $end
$var reg 1 ' q_b1 $end
$var reg 1 ( q_b2 $end
$var reg 1 ) q_b3 $end
$upscope $end
$scope task reset_dut $end
$upscope $end
$scope task send_pulse $end
$upscope $end
$upscope $end
$enddefinitions $end
#0
$dumpvars
x)
x(
x'
x&
x%
0$
0#
x"
x!
$end
#5000
1#
#10000
0'
0(
0)
0!
0&
0%
1"
0#
#12500
1$
#15000
1#
#20000
0#
#25000
1#
0$
#30000
0#
#35000
1#
#37500
1$
#40000
0#
#45000
1#
#50000
0#
0$
#55000
1#
#60000
0"
0#
#62500
1$
#65000
1#
#70000
0#
#75000
1#
0$
#80000
1%
0#
#85000
1&
1#
#87500
1'
1$
#90000
0%
0#
#95000
1#
#100000
0#
0$
#105000
1#
#110000
0#
#112500
1(
1$
#115000
1#
#120000
0#
#125000
1#
0$
#130000
0#
#135000
1#
#137500
1!
1)
1$
#140000
0#
#145000
1#
#150000
0#
0$
#155000
1#
#160000
0#
#162500
0!
1$
